{
  "keys": {
    "XABLAU-7d-GMQTHAFG": {
      "active": true,
      "owner": "RICK | ST",
      "first_use": null,
      "perm": false,
      "duration": "7d"
    },
    "hegsk-#%{}-key": {
      "active": true,
      "owner": "izza",
      "first_use": null,
      "perm": false,
      "duration": "2d"
    },
    "KJWBDODYBQUSHGS": {
      "duration": "7d",
      "active": true,
      "owner": "99524",
      "first_use": 1764813162741,
      "perm": false,
      "device_limit": 1
    },
    "GQ2WGE0GF9L30HFP": {
      "active": true,
      "owner": "FREE GROUP",
      "first_use": 1765184595182,
      "perm": false,
      "duration": "20m"
    },
    "XABLAU-7d-D1V2XHP3": {
      "active": true,
      "owner": "apela",
      "first_use": 1764124424504,
      "perm": false,
      "duration": "7d"
    },
    "sparkdono22": {
      "duration": "12mo",
      "active": true,
      "owner": "DONO",
      "first_use": 1764607696277,
      "perm": false,
      "device_limit": 1
    },
    "KEY-KHJUWBYAVDU": {
      "duration": "5d",
      "active": true,
      "owner": "MIGUEL | ST",
      "first_use": 1765068418639,
      "perm": false,
      "device_limit": 1
    },
    "KEY-WY64ADQ6QYE7": {
      "device_limit": 1,
      "active": true,
      "owner": "GRÁTIS",
      "first_use": 1764358308288,
      "perm": false,
      "duration": "20m"
    },
    "KYQVXUNDIJQBAYF": {
      "device_limit": 1,
      "active": true,
      "owner": "?? | SC",
      "first_use": 1765075266691,
      "perm": false,
      "duration": "7d"
    },
    "NKW7HA5BXY6HW": {
      "duration": "1m",
      "active": true,
      "owner": "RAIO",
      "first_use": null,
      "device_limit": 1,
      "perm": false
    },
    "KEY-VWUVG1ZBF2HNS5T3": {
      "active": true,
      "owner": "KEYs GRÁTIS NO GRUPO 🆓",
      "first_use": null,
      "perm": false,
      "duration": "10m"
    },
    "KEY-A50PXS6OVRVIIEGC": {
      "active": true,
      "owner": "DOLLY | SC",
      "first_use": 1765174847723,
      "perm": false,
      "duration": "7d"
    },
    "XABLAU-1d-TEE8B9P3": {
      "active": true,
      "owner": "apela",
      "first_use": 1764280394173,
      "perm": false,
      "duration": "1d"
    },
    "CUSCUZ-01": {
      "perm": false,
      "active": true,
      "owner": "??? | SC - ST",
      "first_use": 1764902476231,
      "device_limit": 1,
      "duration": "12mo"
    },
    "GHYAT4TWQC43GWYA": {
      "perm": false,
      "active": true,
      "owner": "MARQUINHOS | SC",
      "first_use": 1764625402035,
      "device_limit": 1,
      "duration": "7d"
    },
    "KJHTJAYXBAURBD": {
      "perm": false,
      "active": true,
      "owner": "MEIDEUS",
      "first_use": 1765154027630,
      "device_limit": 1,
      "duration": "7d"
    },
    "KJ3HWY4GXYVQKZY": {
      "perm": false,
      "active": true,
      "owner": "RNZIN | ST",
      "first_use": null,
      "device_limit": 1,
      "duration": "7d"
    },
    "https-#%{}3654-KEY": {
      "active": true,
      "owner": "iOS",
      "first_use": null,
      "perm": false,
      "duration": "2d"
    },
    "heads-89125#-key": {
      "active": true,
      "owner": "Kayky",
      "first_use": 1764114781838,
      "perm": false,
      "duration": "10d"
    },
    "XABLAU-KS5QJA68NS": {
      "duration": "1d",
      "active": true,
      "owner": "LV CHATO ( SITE )",
      "first_use": null,
      "perm": false,
      "device_limit": 1
    },
    "XABLAU-7d-QHR3J2JS": {
      "active": true,
      "owner": "gay",
      "first_use": null,
      "perm": false,
      "duration": "7d"
    },
    "XABLAU-7d-XQEH6ED2": {
      "active": true,
      "owner": "nalber",
      "first_use": 1764292087761,
      "perm": false,
      "duration": "7d"
    },
    "hjsg-##23213-key": {
      "active": true,
      "owner": "bnzin",
      "first_use": 1764189781608,
      "perm": false,
      "duration": "1d"
    },
    "XABLAU-7d-WQ5BD2YA": {
      "active": true,
      "owner": "CLIENTE AYUMI ( SC )",
      "first_use": 1764020827075,
      "perm": false,
      "duration": "7d"
    },
    "H565PV2SSX3QG8U9": {
      "active": true,
      "owner": "FREE GROUP",
      "first_use": 1765179321232,
      "perm": false,
      "duration": "20m"
    },
    "XABLAU-4d-H217UE4A": {
      "active": true,
      "owner": "Hugo",
      "first_use": null,
      "perm": false,
      "duration": "4d"
    },
    "gsjdhd-#}{}%^-key": {
      "active": true,
      "owner": "izza",
      "first_use": 1764597952965,
      "perm": false,
      "duration": "3d"
    },
    "hdh-%%#}1-key": {
      "active": true,
      "owner": "Hugo",
      "first_use": 1764457931313,
      "perm": false,
      "duration": "3d"
    },
    "sparkii": {
      "active": true,
      "owner": "ss",
      "first_use": 1765158644249,
      "perm": false,
      "duration": "10d"
    },
    "KEY-OZUR2T25FW2J4GKB": {
      "active": true,
      "owner": "KEYs GRÁTIS NO GRUPO 🆓",
      "first_use": null,
      "perm": false,
      "duration": "10m"
    },
    "XABLAU-1d-LJK2I865": {
      "active": true,
      "owner": "grátis",
      "first_use": 1764114068463,
      "perm": false,
      "duration": "1d"
    },
    "XABLAU-35d-LK1Q567U": {
      "active": true,
      "owner": "WEVE ( ST )",
      "first_use": null,
      "perm": false,
      "duration": "35d"
    },
    "XABLAU-7d-WJ85OXUN": {
      "active": true,
      "owner": "LUCAS SILVA ( ? )",
      "first_use": 1764126409493,
      "perm": false,
      "duration": "7d"
    },
    "KABYXBAIUVWYOUFB": {
      "duration": "5d",
      "active": true,
      "owner": "L7 | ST",
      "first_use": 1765105863722,
      "perm": false,
      "device_limit": 1
    },
    "XABLAU-2d-XNLIN6YS": {
      "active": true,
      "owner": "viadin",
      "first_use": null,
      "perm": false,
      "duration": "2d"
    },
    "XABLAU-1d-DW7NK4YC": {
      "active": true,
      "owner": "CLIENTE MOREIRA",
      "first_use": 1763971234584,
      "perm": false,
      "duration": "1d"
    },
    "XABLAU-7d-8OLJDUFA": {
      "active": true,
      "owner": "acerola",
      "first_use": 1764166509542,
      "perm": false,
      "duration": "7d"
    },
    "KW4HAIY5GW5BWY": {
      "device_limit": 1,
      "active": true,
      "owner": "VICTOR | SC",
      "first_use": 1764626777070,
      "perm": false,
      "duration": "7d"
    },
    "XABLAU-PERM-UY5IDGBFYN": {
      "active": true,
      "owner": "DONO XABLAU",
      "first_use": 1763991241690,
      "perm": false,
      "duration": "12M"
    },
    "XABLAU-7d-0QCIEZ99": {
      "active": true,
      "owner": "DOLLY | IOS",
      "first_use": null,
      "perm": false,
      "duration": "7d"
    },
    "apelaxablauffx-seconds-jlwBvS1SRte7HLFI": {
      "active": true,
      "owner": "kk",
      "first_use": 1765177917178,
      "perm": false,
      "duration": "6s"
    },
    "XABLAU-1d-Z8KNUBML": {
      "active": true,
      "owner": "apela",
      "first_use": 1764220055077,
      "perm": false,
      "duration": "1d"
    },
    "XABLAU-7d-33H8QXR1": {
      "active": true,
      "owner": "91 992949977 ( ST )",
      "first_use": null,
      "perm": false,
      "duration": "7d"
    },
    "XABLAU-10d-36KHUTKG": {
      "active": true,
      "owner": "viado",
      "first_use": 1764199934689,
      "perm": false,
      "duration": "10d"
    },
    "ENQBNW8E9T5BP3Q9": {
      "active": true,
      "owner": "FREE GROUP",
      "first_use": 1765180275163,
      "perm": false,
      "duration": "20m"
    },
    "KEY-US5HA4VAFA44TW": {
      "device_limit": 1,
      "active": true,
      "owner": "MIGUEL | ST",
      "first_use": 1764607229704,
      "perm": false,
      "duration": "7d"
    },
    "KJYAYBAXTAJCR": {
      "duration": "7d",
      "active": true,
      "owner": "sh",
      "first_use": null,
      "perm": false,
      "device_limit": 1
    },
    "GRATIS-WJ63XINZL": {
      "duration": "1h",
      "active": true,
      "owner": "KEY GRÁTIS",
      "first_use": 1764251714623,
      "device_limit": 1,
      "perm": false
    },
    "XABLAU-7d-G2V5PPWZ": {
      "active": true,
      "owner": "MAYKE ( ST )",
      "first_use": null,
      "perm": false,
      "duration": "7d"
    },
    "NJ5HW5GWG9BWUX0": {
      "device_limit": 1,
      "active": true,
      "owner": "MARQUINHOS | SC",
      "first_use": 1764627884570,
      "perm": false,
      "duration": "10d"
    },
    "ID6UWNX2UWN5WH": {
      "duration": "7d",
      "active": true,
      "owner": "RAIO",
      "first_use": null,
      "perm": false,
      "device_limit": 1
    },
    "hdhsg-#62582-%-": {
      "active": true,
      "owner": "higor",
      "first_use": 1764482763291,
      "perm": false,
      "duration": "4d"
    },
    "LVZADA": {
      "perm": false,
      "active": true,
      "owner": "lvdapaz",
      "first_use": null,
      "device_limit": 3,
      "duration": "12M"
    },
    "KEY-5d-E3S8SCXK": {
      "perm": false,
      "active": true,
      "owner": "KN",
      "first_use": 1764898008744,
      "device_limit": 1,
      "duration": "5d"
    },
    "IWBXYTSUIXUWBX": {
      "device_limit": 1,
      "active": true,
      "owner": "DOGUINHA | ST",
      "first_use": null,
      "perm": false,
      "duration": "7d"
    },
    "WK5GS6HBAUKSUCJ": {
      "perm": false,
      "active": true,
      "owner": "WILLIAM | ST",
      "first_use": 1764801338897,
      "device_limit": 1,
      "duration": "7d"
    },
    "apelaxablauffx-days-lPIgrnrr1zYWcMGV": {
      "active": true,
      "owner": "NAO SEI",
      "first_use": 1765178385701,
      "perm": false,
      "duration": "7d"
    },
    "KEY-SFYCI9EWL547TGCW": {
      "active": true,
      "owner": "KEYs GRÁTIS NO GRUPO 🆓",
      "first_use": 1765224995519,
      "perm": false,
      "duration": "10m"
    },
    "KEY-7d-XDWDZZU7": {
      "perm": false,
      "active": true,
      "owner": "CLIENTE 2 | SC",
      "first_use": 1765057969551,
      "device_limit": 1,
      "duration": "7d"
    },
    "sparki": {
      "active": true,
      "owner": "SENAO",
      "first_use": 1765157259890,
      "perm": false,
      "duration": "10s"
    },
    "hjsjs-##%-key": {
      "active": true,
      "owner": "Hugo",
      "first_use": 1765146495228,
      "perm": false,
      "duration": "3d"
    },
    "KEY-WHCYAPBRYVD": {
      "duration": "1d",
      "active": true,
      "owner": "carinha",
      "first_use": 1765051222255,
      "device_limit": 1,
      "perm": false
    },
    "XABLAU-7d-J0K3W183": {
      "active": true,
      "owner": "apela",
      "first_use": 1764283771867,
      "perm": false,
      "duration": "7d"
    },
    "I64LL5J1HJEXLO4X": {
      "active": true,
      "owner": "FREE GROUP",
      "first_use": null,
      "perm": false,
      "duration": "20m"
    },
    "KEY-NK6WY5G33HQNX": {
      "perm": false,
      "active": true,
      "owner": "GUMAO | SC",
      "first_use": 1764603376394,
      "device_limit": 1,
      "duration": "3d"
    },
    "#%#-15252-key": {
      "active": true,
      "owner": "ioss",
      "first_use": 1764347675341,
      "perm": false,
      "duration": "2d"
    },
    "KEY-4s-RVI648YN": {
      "duration": "4s",
      "active": true,
      "owner": "MEIDEUS",
      "first_use": null,
      "device_limit": 1,
      "perm": false
    },
    "apelaxablauffx-seconds-igmKEWyCGKUyq2Pl": {
      "active": true,
      "owner": "❤️❤️❤️❤️❤️❤️❤️❤️❤️❤️❤️❤️❤️❤️❤️❤️❤️❤️❤️❤️",
      "first_use": 1765225428502,
      "perm": false,
      "duration": "6s"
    },
    "XABLAU-7d-HFV3KI7O": {
      "active": true,
      "owner": "CLIENTE 66YX ( ST )",
      "first_use": null,
      "perm": false,
      "duration": "7d"
    },
    "IAF5F3JOWL97FUDG": {
      "active": true,
      "owner": "FREE GROUP",
      "first_use": 1765179281269,
      "perm": false,
      "duration": "20m"
    },
    "hsgeg-#%*-key": {
      "active": true,
      "owner": "higor",
      "first_use": null,
      "perm": false,
      "duration": "5d"
    },
    "11H22NSB9CAD7ILZ": {
      "active": true,
      "owner": "VN FIOTÃO | IOS",
      "first_use": 1765207102807,
      "perm": false,
      "duration": "5d"
    },
    "KEY-SQ5T17HW5YWG61G": {
      "device_limit": 1,
      "active": true,
      "owner": "ANGELA DIAS GRTS ( SC )",
      "first_use": 1764480645988,
      "perm": false,
      "duration": "1d"
    },
    "XABLAU-7d-3UXQEVF2": {
      "active": true,
      "owner": "apelaxablau",
      "first_use": 1764114020431,
      "perm": false,
      "duration": "7d"
    }
  }
}